cppToPythonHelper/HelloWorld.py
cppToPythonHelper/__init__.py
cppToPythonHelper/std.py
cppToPythonHelper-0.0.1.dist-info/LICENSE
cppToPythonHelper-0.0.1.dist-info/METADATA
cppToPythonHelper-0.0.1.dist-info/WHEEL
cppToPythonHelper-0.0.1.dist-info/top_level.txt
cppToPythonHelper-0.0.1.dist-info/RECORD
