Metadata-Version: 2.1
Name: cppToPythonHelper
Version: 0.0.1
Summary: A Package to help C++ developers transition to python
Home-page: https://github.com/xavierdmello/std
Author: Xavier D
License: MIT
Platform: UNKNOWN
License-File: LICENSE
